{
    "plugin": "jetpack/jetpack",
    "status": "active",
    "name": "Jetpack",
    "plugin_uri": "https://jetpack.com",
    "author": "Automattic",
    "author_uri": "https://jetpack.com",
    "description": {
        "raw": "Security, performance, and marketing tools made by WordPress experts. Jetpack keeps your site protected so you can focus on more important things.",
        "rendered": "Security, performance, and marketing tools made by WordPress experts. Jetpack keeps your site protected so you can focus on more important things. <cite>By <a href=\"https://jetpack.com\">Automattic</a>.</cite>"
    },
    "version": "11.5.1",
    "network_only": false,
    "requires_wp": "6.0",
    "requires_php": "5.6",
    "textdomain": "jetpack",
    "_links": {
        "self": [
            {
                "href": "https://test.com/wp-json/wp/v2/plugins/jetpack/jetpack"
            }
        ]
    }
}
